zarabaza.py
zarabaza-0.0.10.dist-info/METADATA
zarabaza-0.0.10.dist-info/WHEEL
zarabaza-0.0.10.dist-info/RECORD
